{
  "defaultLocale": "en",
  "locales": [
    "en",
    "fr",
    "pt-br",
    "es"
  ],
  "path": "i18n",
  "currentLocale": "es",
  "localeConfigs": {
    "en": {
      "label": "English",
      "direction": "ltr",
      "htmlLang": "en",
      "calendar": "gregory",
      "path": "en"
    },
    "fr": {
      "label": "Français",
      "direction": "ltr",
      "htmlLang": "fr",
      "calendar": "gregory",
      "path": "fr"
    },
    "pt-br": {
      "label": "Português (Brasil)",
      "direction": "ltr",
      "htmlLang": "pt-br",
      "calendar": "gregory",
      "path": "pt-br"
    },
    "es": {
      "label": "Español",
      "direction": "ltr",
      "htmlLang": "es",
      "calendar": "gregory",
      "path": "es"
    }
  }
}